jsoncolor/__init__.py
jsoncolor/_compat.py
jsoncolor/cli.py
jsoncolor/config.py
jsoncolor/core.py
jsoncolor/errors.py
jsoncolor-0.2.dist-info/DESCRIPTION.rst
jsoncolor-0.2.dist-info/METADATA
jsoncolor-0.2.dist-info/RECORD
jsoncolor-0.2.dist-info/WHEEL
jsoncolor-0.2.dist-info/entry_points.txt
jsoncolor-0.2.dist-info/metadata.json
jsoncolor-0.2.dist-info/top_level.txt
