Metadata-Version: 2.0
Name: jsoncolor
Version: 0.2
Summary: A JSON content terminal coloring tool
Home-page: https://github.com/json-transformations/jsoncolor
Author: Tim Phillips
Author-email: phillipstr@gmail.com
License: UNKNOWN
Platform: UNKNOWN
Classifier: License :: OSI Approved :: MIT License
Classifier: Programming Language :: Python
Classifier: Programming Language :: Python :: 2
Classifier: Programming Language :: Python :: 3
Classifier: Topic :: Utilities
Requires-Dist: jsoncore (>=0.6.8)
Requires-Dist: jsonconfig-tool
Requires-Dist: click (>=6.0)
Requires-Dist: pygments
